pykeys/__init__.py
pykeys/alternate_init.py
pykeys/alternate_init2.py
pykeys/encryption.py
pykeys/test_unit.py
pykeys/utilities.py
pykeys/vault.py
pykeys-19.1.0.dist-info/LICENSE
pykeys-19.1.0.dist-info/METADATA
pykeys-19.1.0.dist-info/WHEEL
pykeys-19.1.0.dist-info/top_level.txt
pykeys-19.1.0.dist-info/RECORD
